dictDigUtils.py
dictDigUtils-1.0.3.dist-info/METADATA
dictDigUtils-1.0.3.dist-info/WHEEL
dictDigUtils-1.0.3.dist-info/top_level.txt
dictDigUtils-1.0.3.dist-info/RECORD
