Metadata-Version: 2.1
Name: dictDigUtils
Version: 1.0.3
Author-email: Tomio13 <haraszti@dwi.rwth-aachen.de>
Classifier: Programming Language :: Python :: 3
Classifier: License :: OSI Approved :: MIT License
Classifier: Operating System :: OS Independent
